odoo10_addon_partner_contact_birthplace-10.0.1.0.0-py2.7-nspkg.pth
odoo/addons/partner_contact_birthplace/README.rst
odoo/addons/partner_contact_birthplace/__init__.py
odoo/addons/partner_contact_birthplace/__manifest__.py
odoo/addons/partner_contact_birthplace/i18n/it.po
odoo/addons/partner_contact_birthplace/models/__init__.py
odoo/addons/partner_contact_birthplace/models/res_partner.py
odoo/addons/partner_contact_birthplace/static/description/icon.png
odoo/addons/partner_contact_birthplace/views/res_partner.xml
odoo10_addon_partner_contact_birthplace-10.0.1.0.0.dist-info/DESCRIPTION.rst
odoo10_addon_partner_contact_birthplace-10.0.1.0.0.dist-info/METADATA
odoo10_addon_partner_contact_birthplace-10.0.1.0.0.dist-info/RECORD
odoo10_addon_partner_contact_birthplace-10.0.1.0.0.dist-info/WHEEL
odoo10_addon_partner_contact_birthplace-10.0.1.0.0.dist-info/metadata.json
odoo10_addon_partner_contact_birthplace-10.0.1.0.0.dist-info/namespace_packages.txt
odoo10_addon_partner_contact_birthplace-10.0.1.0.0.dist-info/top_level.txt
