Metadata-Version: 2.0
Name: odoo10-addon-partner-contact-birthplace
Version: 10.0.1.0.0
Summary: This module allows to define a birthplace for partners.
Home-page: https://github.com/OCA/partner-contact/tree/10.0/partner_contact_birthplace
Author: Agile Business Group, Odoo Community Association (OCA)
Author-email: support@odoo-community.org
License: AGPL-3
Platform: UNKNOWN
Classifier: Programming Language :: Python
Classifier: Framework :: Odoo
Classifier: License :: OSI Approved :: GNU Affero General Public License v3
Requires-Python: ~=2.7
Requires-Dist: odoo (<10.1dev,>=10.0)
Requires-Dist: odoo10-addon-partner-contact-personal-information-page
